jupyterhub_share_link_serverextension/__init__.py
jupyterhub_share_link_serverextension/_version.py
jupyterhub_share_link_serverextension/tests/__init__.py
jupyterhub_share_link_serverextension/tests/conftest.py
jupyterhub_share_link_serverextension/tests/test_imports.py
jupyterhub_share_link_serverextension-0.1.0.dist-info/METADATA
jupyterhub_share_link_serverextension-0.1.0.dist-info/RECORD
jupyterhub_share_link_serverextension-0.1.0.dist-info/WHEEL
jupyterhub_share_link_serverextension-0.1.0.dist-info/entry_points.txt
jupyterhub_share_link_serverextension-0.1.0.dist-info/top_level.txt
