Metadata-Version: 2.1
Name: jupyterhub-share-link-serverextension
Version: 0.1.0
Summary: Python package for doing science.
Home-page: https://github.com/danielballan/jupyterhub-share-link-serverextension
Author: JupyterHub Share Link Contributors
Author-email: dallan@bnl.gov
License: BSD (3-clause)
Platform: UNKNOWN
Classifier: Development Status :: 2 - Pre-Alpha
Classifier: Natural Language :: English
Classifier: Programming Language :: Python :: 3
Requires-Python: >=3.6
Requires-Dist: jupyterlab (>=1.0.0)
